qwasm/__init__.py
qwasm/__main__.py
qwasm/compat.py
qwasm/decode.py
qwasm/formatter.py
qwasm/immtypes.py
qwasm/modtypes.py
qwasm/opcodes.py
qwasm/types.py
qwasm/wasmtypes.py
qwasm-1.0.dist-info/LICENSE
qwasm-1.0.dist-info/METADATA
qwasm-1.0.dist-info/WHEEL
qwasm-1.0.dist-info/entry_points.txt
qwasm-1.0.dist-info/top_level.txt
qwasm-1.0.dist-info/RECORD
