Metadata-Version: 2.1
Name: qwasm
Version: 1.0
Summary: WebAssembly decoder & disassembler
Author: Melf Johannsen
Author-email: melf.johannsen@quantinuum.com
License: MIT
Keywords: wasm,disassembler,decoder
License-File: LICENSE
Requires-Dist: setuptools
